Metadata-Version: 2.1
Name: typedpy
Version: 2.28.3
Summary: Type-safe Python
Home-page: http://github.com/loyada/typedpy
Author: Danny Loya
Author-email: dan.loya@gmail.com
License: MIT
Download-URL: https://github.com/loyada/typedpy/archive/v2.28.3.tar.gz
Keywords: testing,type-safe,strict,schema,validation
Platform: UNKNOWN
Classifier: Development Status :: 5 - Production/Stable
Classifier: Intended Audience :: Developers
Classifier: License :: OSI Approved :: MIT License
Classifier: Operating System :: OS Independent
Classifier: Programming Language :: Python
Classifier: Programming Language :: Python :: 3.9
Classifier: Programming Language :: Python :: 3.10
Classifier: Programming Language :: Python :: 3.11
Classifier: Programming Language :: Python :: 3.12
License-File: LICENSE.txt
